fbf-0.0.0a0.dist-info/METADATA
fbf-0.0.0a0.dist-info/WHEEL
fbf-0.0.0a0.dist-info/entry_points.txt
fbf-0.0.0a0.dist-info/license_files/LICENSE
fbf/cell.py
fbf/py.typed
fbf/run.py
fbf/ybsm.pyi
fbf/__init__.py
fbf/__main__.py
fbf/ybsm.cp312-win_amd64.pyd
fbf-0.0.0a0.dist-info/RECORD
